up_spiderplan/__init__.py
up_spiderplan/converter.py
up_spiderplan/solver.py
up_spiderplan/util.py
up_spiderplan-0.6.4.dist-info/LICENSE
up_spiderplan-0.6.4.dist-info/METADATA
up_spiderplan-0.6.4.dist-info/WHEEL
up_spiderplan-0.6.4.dist-info/top_level.txt
up_spiderplan-0.6.4.dist-info/RECORD
