Metadata-Version: 2.1
Name: up-spiderplan
Version: 0.6.4
Summary: Spiderplan engine for the Unified Planning Library
Home-page: https://github.com/aiplan4eu/up-spiderplan/
Author: Uwe Köckemann
Author-email: uwe.kockemann@oru.se
License: UNKNOWN
Project-URL: Bug Tracker, https://github.com/aiplan4eu/up-spiderplan/issues
Platform: UNKNOWN
Classifier: Programming Language :: Python :: 3
Classifier: License :: OSI Approved :: GNU General Public License v3 (GPLv3)
Classifier: Operating System :: OS Independent
Requires-Python: >=3.7
License-File: LICENSE
Requires-Dist: aiddl-core (==0.3.0)
Requires-Dist: aiddl-external-grpc (==0.1.4)
Requires-Dist: matplotlib (==3.5.3)
Requires-Dist: unified-planning (>=1.0.0)
